ddd_struct/__init__.py
ddd_struct/version.py
ddd_struct/application/__init__.py
ddd_struct/application/action.py
ddd_struct/domain/__init__.py
ddd_struct/domain/repository.py
ddd_struct/infrastructure/__init__.py
ddd_struct/infrastructure/repository_impl.py
ddd_struct/lib/__init__.py
ddd_struct/lib/common.py
ddd_struct/lib/thread.py
ddd_struct/lib/warning.py
ddd_struct-0.2.6.dist-info/LICENSE
ddd_struct-0.2.6.dist-info/METADATA
ddd_struct-0.2.6.dist-info/WHEEL
ddd_struct-0.2.6.dist-info/top_level.txt
ddd_struct-0.2.6.dist-info/RECORD
