Metadata-Version: 2.1
Name: ddd-struct
Version: 0.2.6
Summary: Data structures
Author: wangziling100
Author-email: wangziling100@163.com
Classifier: Programming Language :: Python :: 3
Classifier: License :: OSI Approved :: MIT License
License-File: LICENSE
Requires-Dist: retry2
Requires-Dist: ddd-interface
Requires-Dist: psutil
